odoo/addons/project_task_note/README.rst
odoo/addons/project_task_note/__init__.py
odoo/addons/project_task_note/__manifest__.py
odoo/addons/project_task_note/i18n/es.po
odoo/addons/project_task_note/i18n/it.po
odoo/addons/project_task_note/i18n/project_task_note.pot
odoo/addons/project_task_note/i18n/pt_BR.po
odoo/addons/project_task_note/models/__init__.py
odoo/addons/project_task_note/models/project_task.py
odoo/addons/project_task_note/readme/CONTEXT.md
odoo/addons/project_task_note/readme/CONTRIBUTORS.md
odoo/addons/project_task_note/readme/DESCRIPTION.md
odoo/addons/project_task_note/readme/USAGE.srt
odoo/addons/project_task_note/static/description/icon.png
odoo/addons/project_task_note/static/description/index.html
odoo/addons/project_task_note/views/project_task_views.xml
odoo_addon_project_task_note-18.0.1.0.0.3.dist-info/METADATA
odoo_addon_project_task_note-18.0.1.0.0.3.dist-info/WHEEL
odoo_addon_project_task_note-18.0.1.0.0.3.dist-info/top_level.txt
odoo_addon_project_task_note-18.0.1.0.0.3.dist-info/RECORD
